depalert/__init__.py
depalert-0.0.1.dist-info/METADATA
depalert-0.0.1.dist-info/WHEEL
depalert-0.0.1.dist-info/top_level.txt
depalert-0.0.1.dist-info/RECORD
