Metadata-Version: 2.4
Name: depalert
Version: 0.0.1
Summary: Security placeholder for DepAlert tool
Home-page: https://github.com/CyberGabiSoft/depalert
Author: CyberGabi Team
Author-email: security@chainthreatwall.com
Project-URL: Bug Tracker, https://github.com/CyberGabiSoft/depalert/issues
Classifier: Programming Language :: Python :: 3
Classifier: License :: OSI Approved :: MIT License
Classifier: Operating System :: OS Independent
Classifier: Development Status :: 1 - Planning
Requires-Python: >=3.6
Dynamic: author
Dynamic: author-email
Dynamic: classifier
Dynamic: description
Dynamic: description-content-type
Dynamic: home-page
Dynamic: project-url
Dynamic: requires-python
Dynamic: summary
